lean_transformer
